tomifier/__init__.py
tomifier/addcmd.py
tomifier/cli.py
tomifier/defaults.py
tomifier/fileutils.py
tomifier/initcmd.py
tomifier/validation.py
tomifier/version.py
tomifier-0.0.7.dist-info/LICENSE
tomifier-0.0.7.dist-info/METADATA
tomifier-0.0.7.dist-info/WHEEL
tomifier-0.0.7.dist-info/entry_points.txt
tomifier-0.0.7.dist-info/top_level.txt
tomifier-0.0.7.dist-info/RECORD
