Metadata-Version: 2.1
Name: tomifier
Version: 0.0.7
Summary: A simple pyproject.toml initiator
Author-email: Alex Morales <am8850mia@gmail.com>
License: MIT License
Project-URL: Homepage, https://github.com/am8850/tomifier
Classifier: Programming Language :: Python :: 3
Classifier: Operating System :: OS Independent
Requires-Python: >=3.10
License-File: LICENSE
Requires-Dist: click
Requires-Dist: build
Requires-Dist: requests
